{"errors":[],"warnings":[],"version":"1.12.9","hash":"d0f47a500a2f8dc985ff","publicPath":"https://cdn.smooch.io/","assetsByChunkName":{"clare":["clare.js","clare.js.map"]},"assets":[{"name":"62d66710100627758e2ad0721374a338.png","size":6009,"chunks":[],"chunkNames":[],"emitted":true},{"name":"f6315ad3b31c550f804e52a12db60a2b.png","size":37413,"chunks":[],"chunkNames":[],"emitted":true},{"name":"f97e3bbf73254b0112091d0192f17aec.svg","size":2152,"chunks":[],"chunkNames":[],"emitted":true},{"name":"4fc55e74cd731f89b3cf2c1cd4aaf471.png","size":63428,"chunks":[],"chunkNames":[],"emitted":true},{"name":"a4c1e7e6066665926d65ea3e390f2897.mp3","size":28211,"chunks":[],"chunkNames":[],"emitted":true},{"name":"8ddaae5507ef13e91e228c0494fd0ae1.png","size":1498,"chunks":[],"chunkNames":[],"emitted":true},{"name":"cf7d50f932399b510d57cd887c902680.png","size":2134,"chunks":[],"chunkNames":[],"emitted":true},{"name":"81567450d8214329730cd429cb4083ff.png","size":2461,"chunks":[],"chunkNames":[],"emitted":true},{"name":"be3521c4cdb428a90dc223e76ab16f32.png","size":4137,"chunks":[],"chunkNames":[],"emitted":true},{"name":"d7e8b61376385a28b28e39f1d540763c.png","size":1874,"chunks":[],"chunkNames":[],"emitted":true},{"name":"8d6e8ba2b2bbcd3a28f1b648d41933a5.png","size":2881,"chunks":[],"chunkNames":[],"emitted":true},{"name":"3a9b9d0f58b2c72b377140b1785431f3.png","size":3411,"chunks":[],"chunkNames":[],"emitted":true},{"name":"8a4e62acad2efc17712c6ee9bf817e87.png","size":5858,"chunks":[],"chunkNames":[],"emitted":true},{"name":"787ea80778a3c39701aa69acbcb53035.png","size":2653,"chunks":[],"chunkNames":[],"emitted":true},{"name":"aaf51119496251b312bcad32d30ec32e.png","size":5616,"chunks":[],"chunkNames":[],"emitted":true},{"name":"d09ec94c653fc85b4f63d731cf72d4b6.png","size":7326,"chunks":[],"chunkNames":[],"emitted":true},{"name":"8c27f1d2bde87b2694039a9f62aee117.png","size":18084,"chunks":[],"chunkNames":[],"emitted":true},{"name":"3d749cd8b8acdedf5946eda8262a8d50.png","size":1786,"chunks":[],"chunkNames":[],"emitted":true},{"name":"306759ba7ce35ad0661700c7fc36436f.png","size":2783,"chunks":[],"chunkNames":[],"emitted":true},{"name":"dd2e95e53165b41a8cfc5a619503c7b4.png","size":3749,"chunks":[],"chunkNames":[],"emitted":true},{"name":"c5cd7f5300576ab4c88202b42f6ded62.gif","size":4178,"chunks":[],"chunkNames":[],"emitted":true},{"name":"2bc532f57a2074a56fc036334188e40a.png","size":1697,"chunks":[],"chunkNames":[],"emitted":true},{"name":"a04c744232a3e4641901aa7eab43e4c9.png","size":2568,"chunks":[],"chunkNames":[],"emitted":true},{"name":"83c94bf974d59ac0ed59f8a69b48bdcf.png","size":2994,"chunks":[],"chunkNames":[],"emitted":true},{"name":"789661b37d36dbe43de410be5859046e.png","size":5242,"chunks":[],"chunkNames":[],"emitted":true},{"name":"9d69b94a58a6503b6d6723476ebba41e.png","size":1650,"chunks":[],"chunkNames":[],"emitted":true},{"name":"ed19ebc9f250c552758aa8bc1a52930e.png","size":2397,"chunks":[],"chunkNames":[],"emitted":true},{"name":"b1d879a94d135c4586d499f377bc7418.png","size":2865,"chunks":[],"chunkNames":[],"emitted":true},{"name":"3bb5fdadad6d0bb8b1a006e7cfa18c5f.png","size":4915,"chunks":[],"chunkNames":[],"emitted":true},{"name":"2b5e86da0f91443e8a83f7883ca9d10f.png","size":1698,"chunks":[],"chunkNames":[],"emitted":true},{"name":"c29f8c28476fc435a2d84a2679d3edd7.png","size":2672,"chunks":[],"chunkNames":[],"emitted":true},{"name":"bca0d1056c4ee94c28fdc9b05f79e1d8.png","size":3175,"chunks":[],"chunkNames":[],"emitted":true},{"name":"01cdbc116ccf9464f924722b7be66b25.png","size":5637,"chunks":[],"chunkNames":[],"emitted":true},{"name":"14684ebc028ec8d2c2ad7d431d1957db.png","size":1582,"chunks":[],"chunkNames":[],"emitted":true},{"name":"a505bdd3e591589f1df44ff5c0be94b5.png","size":2129,"chunks":[],"chunkNames":[],"emitted":true},{"name":"ea99c83de67c9d5fd28b06e4b383b3ca.png","size":2481,"chunks":[],"chunkNames":[],"emitted":true},{"name":"67b85b2569bfa2c428b5880cefdc5801.png","size":3871,"chunks":[],"chunkNames":[],"emitted":true},{"name":"clare.js","size":875823,"chunks":[0],"chunkNames":["clare"],"emitted":true},{"name":"clare.js.map","size":6053035,"chunks":[0],"chunkNames":["clare"],"emitted":true},{"name":"stats.json","size":0,"chunks":[],"chunkNames":[]}],"chunks":[{"id":0,"rendered":true,"initial":true,"entry":true,"extraAsync":false,"size":2449124,"names":["clare"],"files":["clare.js","clare.js.map"],"hash":"29a5e215c031e4d1a40e","parents":[],"modules":[{"id":0,"identifier":"multi clare","name":"multi clare","index":0,"index2":916,"size":40,"cacheable":true,"built":true,"optional":false,"prefetched":false,"chunks":[0],"assets":[],"issuer":null,"profile":{"factory":0,"building":2},"failed":false,"errors":0,"warnings":0,"reasons":[]}],"filteredModules":997,"origins":[{"moduleId":0,"module":"multi clare","moduleIdentifier":"multi clare","moduleName":"multi clare","loc":"","name":"clare","reasons":[]}]}],"modules":[{"id":0,"identifier":"multi clare","name":"multi clare","index":0,"index2":916,"size":40,"cacheable":true,"built":true,"optional":false,"prefetched":false,"chunks":[0],"assets":[],"issuer":null,"profile":{"factory":0,"building":2},"failed":false,"errors":0,"warnings":0,"reasons":[]}],"filteredModules":1056,"children":[]}